convert_to_opus/__init__.py
convert_to_opus/converter.py
convert_to_opus/main.py
convert_to_opus-0.6.0.dist-info/LICENSE
convert_to_opus-0.6.0.dist-info/METADATA
convert_to_opus-0.6.0.dist-info/WHEEL
convert_to_opus-0.6.0.dist-info/entry_points.txt
convert_to_opus-0.6.0.dist-info/top_level.txt
convert_to_opus-0.6.0.dist-info/RECORD
