Metadata-Version: 2.1
Name: convert-to-opus
Version: 0.6.0
Summary: Python GUI program that converts directories of audio files to opus using ffmpeg
Home-page: https://github.com/D221/convert_to_opus
Author: D221
Author-email: D221@airmail.cc
License: UNKNOWN
Platform: UNKNOWN
Classifier: Programming Language :: Python :: 3
Classifier: License :: OSI Approved :: MIT License
Classifier: Operating System :: OS Independent
License-File: LICENSE
Requires-Dist: wxPython (==4.1.1)
